setup.py
nwkautomaniac/__init__.py
nwkautomaniac/bracket_expansion.py
nwkautomaniac/ezcfmaker.py
nwkautomaniac.egg-info/PKG-INFO
nwkautomaniac.egg-info/SOURCES.txt
nwkautomaniac.egg-info/dependency_links.txt
nwkautomaniac.egg-info/top_level.txt